inmanta_plugins/net/__init__.py
inmanta_plugins/net/setup.cfg
inmanta_plugins/net/model/_init.cf
inmanta_module_net-1.1.3.dist-info/METADATA
inmanta_module_net-1.1.3.dist-info/WHEEL
inmanta_module_net-1.1.3.dist-info/top_level.txt
inmanta_module_net-1.1.3.dist-info/RECORD
