Metadata-Version: 2.1
Name: inmanta-module-net
Version: 1.1.3
License: Apache 2.0
Requires-Dist: inmanta-module-std
